{
  "threads": [
    {
      "thread_id": 31597,
      "title": "C011/C012/C013/C014 | Sep 18, 2025",
      "prefix_id": 5,
      "view_url": "https://www.democracycraft.net/threads/c011-c012-c013-c014-sep-18-2025.31597/"
    },
    {
      "thread_id": 31596,
      "title": "C068/C069/C070/C071 | Sep 18, 2025",
      "prefix_id": 5,
      "view_url": "https://www.democracycraft.net/threads/c068-c069-c070-c071-sep-18-2025.31596/"
    },
    {
      "thread_id": 31595,
      "title": "C086/C087 | Sep 18, 2025",
      "prefix_id": 5,
      "view_url": "https://www.democracycraft.net/threads/c086-c087-sep-18-2025.31595/"
    },
    {
      "thread_id": 31589,
      "title": "C130 | Sep 18, 2025",
      "prefix_id": 5,
      "view_url": "https://www.democracycraft.net/threads/c130-sep-18-2025.31589/"
    },
    {
      "thread_id": 31588,
      "title": "C194 | Sep 18, 2025",
      "prefix_id": 5,
      "view_url": "https://www.democracycraft.net/threads/c194-sep-18-2025.31588/"
    },
    {
      "thread_id": 31587,
      "title": "C230 | Sep 18, 2025",
      "prefix_id": 5,
      "view_url": "https://www.democracycraft.net/threads/c230-sep-18-2025.31587/"
    },
    {
      "thread_id": 31586,
      "title": "C310 | Sep 18, 2025",
      "prefix_id": 5,
      "view_url": "https://www.democracycraft.net/threads/c310-sep-18-2025.31586/"
    },
    {
      "thread_id": 31585,
      "title": "C313 | Sep 18, 2025",
      "prefix_id": 5,
      "view_url": "https://www.democracycraft.net/threads/c313-sep-18-2025.31585/"
    },
    {
      "thread_id": 31584,
      "title": "C357/C358 | Sep 18, 2025",
      "prefix_id": 5,
      "view_url": "https://www.democracycraft.net/threads/c357-c358-sep-18-2025.31584/"
    },
    {
      "thread_id": 31583,
      "title": "C394/C395/C396/C397 | Sep 18, 2025",
      "prefix_id": 5,
      "view_url": "https://www.democracycraft.net/threads/c394-c395-c396-c397-sep-18-2025.31583/"
    },
    {
      "thread_id": 31582,
      "title": "C407 | Sep 18, 2025",
      "prefix_id": 5,
      "view_url": "https://www.democracycraft.net/threads/c407-sep-18-2025.31582/"
    },
    {
      "thread_id": 31581,
      "title": "C447 | Sep 18, 2025",
      "prefix_id": 5,
      "view_url": "https://www.democracycraft.net/threads/c447-sep-18-2025.31581/"
    },
    {
      "thread_id": 31580,
      "title": "C478 | Sep 18, 2025",
      "prefix_id": 5,
      "view_url": "https://www.democracycraft.net/threads/c478-sep-18-2025.31580/"
    },
    {
      "thread_id": 31579,
      "title": "C674 | Sep 18, 2025",
      "prefix_id": 5,
      "view_url": "https://www.democracycraft.net/threads/c674-sep-18-2025.31579/"
    },
    {
      "thread_id": 31578,
      "title": "C727 | Sep 18, 2025",
      "prefix_id": 5,
      "view_url": "https://www.democracycraft.net/threads/c727-sep-18-2025.31578/"
    },
    {
      "thread_id": 31575,
      "title": "RH015 | Sep 18, 2025",
      "prefix_id": 5,
      "view_url": "https://www.democracycraft.net/threads/rh015-sep-18-2025.31575/"
    }
  ]
}